verime/__init__.py
verime/verime.py
verime/data/MANIFEST.in
verime/data/pymod.cpp
verime/data/pyproject.toml
verime/data/pysimu.py
verime/data/setup.cfg
verime/data/setup.py
verime/data/simulation_runner.cpp
verime/data/simulation_runner.h
verime/data/template_makefile.mk
verime-2.0.0.dist-info/COPYING
verime-2.0.0.dist-info/METADATA
verime-2.0.0.dist-info/WHEEL
verime-2.0.0.dist-info/entry_points.txt
verime-2.0.0.dist-info/top_level.txt
verime-2.0.0.dist-info/RECORD
