Metadata-Version: 2.1
Name: verime
Version: 2.0.0
Author: 'Charles Momin, Gaëtan Cassiers'
License: GPLv3
Requires-Python: >=3.11
License-File: COPYING
Requires-Dist: build>=1.0.0
